pysyscore/__init__.py
pysyscore/command.py
pysyscore/process.py
pysyscore/registry.py
pysyscore/services.py
pysyscore/system_info.py
pysyscore/utility.py
pysyscore-1.0.0.dist-info/METADATA
pysyscore-1.0.0.dist-info/WHEEL
pysyscore-1.0.0.dist-info/top_level.txt
pysyscore-1.0.0.dist-info/RECORD
