Metadata-Version: 2.4
Name: pysyscore
Version: 1.0.0
Summary: Core System Management Utilities for Windows (Registry, Services, Processes, User Management).
Author: Lethudu70
License: MIT License
Keywords: windows,system-admin,sysadmin,registry,services,os-info
Classifier: Programming Language :: Python :: 3
Classifier: Operating System :: Microsoft :: Windows
Classifier: License :: OSI Approved :: MIT License
Classifier: Development Status :: 4 - Beta
Classifier: Topic :: System :: Systems Administration
Requires-Python: >=3.6
Requires-Dist: pywin32; platform_system == "Windows"
Dynamic: requires-python
